271-HW/delay_mux.v
`timescale 1ns/10ps
module delay_mux (y, Sel, A, B, C, D);
   input A, B, C, D, Sel;
   output y;
   wire Out1, Out2;
   nand #3 M1(Out1, A, B);
   nand #4 M2(Out2, C, D);
   mux M3(y, Out1, Out2, Sel);
endmodule
module mux(y, y1, y2, Sel);
   input y1, y2, Sel;
   output y;
   wire w1, w2;
   or M1(w1, y1, Sel);
   or M2(w2, y2, Sel);
   nand M3(y, w1, w1);
endmodule
module t_delay_mux ();
   reg A, B, C, D, Sel;
   wire y;
   delay_mux M0(y, Sel, A, B, C, D);
   initial
      $monitor($time,,"A=%b, B=%b, C=%b, D=%b, Sel=%b, y=%b", A, B,
      C, D, Sel, y);
   initial begin
      $dumpfile("delay_mux.vcd");
      $dumpvars(0,t_delay_mux);
   end
   initial begin
      #150 $finish;
   end
   initial begin
      #10 A=0; B=0; C=0; D=0; Sel=0;
      #10 A=0; B=0; C=0; D=0; Sel=1;
      #10 A=1; B=0; C=0; D=0; Sel=0;
      #10 A=1; B=0; C=0; D=0; Sel=1;
      #10 A=0; B=1; C=0; D=0; Sel=0;
      #10 A=0; B=1; C=0; D=0; Sel=1;
      #10 A=1; B=1; C=0; D=0; Sel=0;
      #10 A=1; B=1; C=0; D=0; Sel=1;
      #10 A=0; B=0; C=1; D=0; Sel=0;
      #10 A=0; B=0; C=1; D=0; Sel=1;
      #10 A=0; B=0; C=0; D=1; Sel=0;
      #10 A=0; B=0; C=0; D=1; Sel=1;
   end
endmodule

271-HW/delay_mux.vcd
$date
    Mar  3, 2015  21:33:29
$end
$version
    TOOL:	ncsim	14.10-p001
$end
$timescale
    10 ps
$end

$scope module t_delay_mux $end
$var reg       1 !    A  $end
$var reg       1 "    B  $end
$var reg       1 #    C  $end
$var reg       1 $    D  $end
$var reg       1 %    Sel  $end
$var wire      1 &    y  $end

$scope module M0 $end
$var wire      1 '    A  $end
$var wire      1 (    B  $end
$var wire      1 )    C  $end
$var wire      1 *    D  $end
$var wire      1 +    Sel  $end
$var wire      1 &    y  $end
$var wire      1 ,    Out1  $end
$var wire      1 -    Out2  $end

$scope module M3 $end
$var wire      1 ,    y1  $end
$var wire      1 -    y2  $end
$var wire      1 +    Sel  $end
$var wire      1 &    y  $end
$var wire      1 .    w1  $end
$var wire      1 /    w2  $end
$upscope $end

$upscope $end

$upscope $end

$enddefinitions $end
$dumpvars
x!
x"
x#
x$
x%
x&
x'
x(
x)
x*
x+
x,
x-
x.
x/
$end
#1000
0!
0"
0#
0$
0%
0+
0*
0)
0(
0'
#1300
1,
1.
0&
#1400
1-
1/
#2000
1%
1+
#3000
1!
0%
0+
1'
#4000
1%
1+
#5000
0!
1"
0%
0+
1(
0'
#6000
1%
1+
#7000
1!
0%
0+
1'
#7300
0,
0.
1&
#8000
1%
1+
1.
0&
#9000
0!
0"
1#
0%
0+
1)
0(
0'
0.
1&
#9300
1,
1.
0&
#10000
1%
1+
#11000
0#
1$
0%
0+
1*
0)
#12000
1%
1+
