HW-271/compare.v
module compare (A_gt_B, A_lt_B, A_eq_B, A0, A1, B0, B1); 
	output A_gt_B, A_lt_B, A_eq_B;
	input A0, A1, B0, B1;
	nor (A_gt_B, A_lt_B, A_eq_B); or (A_lt_B, w1, w2, w3); and (A_eq_B, w4, w5);
	and (w1, w6, B1);
	and (w2, w6, w7, B0); and (w3, w7, B0, B1); not (w6, A1);
	not (w7, A0);
	xnor (w4, A1, B1);
	xnor (w5, A0, B0); 
endmodule

module test_compare ( );
  wire A_gt_B, A_lt_B, A_eq_B;
  reg  A0, A1, B0, B1;
  compare M1 (A_gt_B, A_lt_B, A_eq_B, A0, A1, B0, B1);
  initial begin
    #100 $finish;
  end
  initial begin
    #10 A0 = 0; A1 = 0; B0 = 0; B1 = 0;
    #10 A0 = 1'b1;
    #10 A0 = 1'b0; A1 = 1'b1;
    #10 A0 = 1'b1;
    #10 B0 = 1'b1;
    #10 B0 = 1'b0; B1 = 1'b1;
    #10 B0 = 1'b1;
    #10 A0 = 0; A1 = 0;
	#10 B0 = 1'b0;
    #10 B0 = 1'b1; B1 = 1'b0;
    #10 B0 = 1'b0;
  end
  initial begin
  	$dumpfile("compare.vcd");
  	$dumpvars(0,test_compare);
  end
endmodule

HW-271/compare.vcd
$date
    Mar 17, 2015  19:24:35
$end
$version
    TOOL:	ncsim	14.10-p001
$end
$timescale
    1 ns
$end

$scope module test_compare $end
$var wire      1 !    A_gt_B  $end
$var wire      1 "    A_lt_B  $end
$var wire      1 #    A_eq_B  $end
$var reg       1 $    A0  $end
$var reg       1 %    A1  $end
$var reg       1 &    B0  $end
$var reg       1 '    B1  $end

$scope module M1 $end
$var wire      1 !    A_gt_B  $end
$var wire      1 "    A_lt_B  $end
$var wire      1 #    A_eq_B  $end
$var wire      1 (    A0  $end
$var wire      1 )    A1  $end
$var wire      1 *    B0  $end
$var wire      1 +    B1  $end
$var wire      1 ,    w3  $end
$var wire      1 -    w2  $end
$var wire      1 .    w1  $end
$var wire      1 /    w5  $end
$var wire      1 0    w4  $end
$var wire      1 1    w6  $end
$var wire      1 2    w7  $end
$upscope $end

$upscope $end

$enddefinitions $end
$dumpvars
x!
x"
x#
x$
x%
x&
x'
x(
x)
x*
x+
x,
x-
x.
x/
x0
x1
x2
$end
#10
0$
0%
0&
0'
0+
0*
0)
0(
11
12
0,
0-
0.
0"
1/
10
1#
0!
#20
1$
1(
02
0/
0#
1!
#30
0$
1%
1)
0(
01
12
1/
00
#40
1$
1(
02
0/
#50
1&
1*
1/
#60
0&
1'
1+
0*
0/
10
#70
1&
1*
1/
1#
0!
#80
0$
0%
0)
0(
11
12
1,
1-
1.
1"
0/
00
0#
#90
0&
0*
0,
0-
1/
