HW-271/problem_2.v
module Problem_2 (Y1, Y2, A, B, C, D);
 output Y1, Y2;
 input A, B, C, D;
 not (A_not, A);
 not (B_not, B);
 not (C_not, C);
 not (D_not, D);
 and (w4, A_not, B, C_not, D_not);
 and (w5, A_not, B, C_not, D);
 and (w6, A_not, B, C, D_not);
and (w7, A_not, B, C, D);
 and (w11, A, B_not, C, D);
 and (w12, A, B, C_not, D_not);
 and (w13, A, B, C_not, D);
 or  (Y1, w4, w5, w6, w7, w11, w12, w13);
 and (w1, A_not, B_not, C_not, D);
 and (w2, A_not, B_not, C, D_not);
 or  (Y2, w1, w2, w4, w5);
endmodule


module t_Problem_2();
 reg A, B, C, D;
 wire Y1, Y2;
 Problem_2 M0 (Y1, Y2, A, B, C, D);
initial
begin
$dumpfile("problem_2.vcd");
$dumpvars(0,t_Problem_2);
end 

initial begin
   #5 {A, B, C, D} = 4'b0000;
   #5 {A, B, C, D} = 4'b0001;
   #5 {A, B, C, D} = 4'b0010;
   #5 {A, B, C, D} = 4'b0011;
   #5 {A, B, C, D} = 4'b0100;
   #5 {A, B, C, D} = 4'b0101;
   #5 {A, B, C, D} = 4'b0110;
   #5 {A, B, C, D} = 4'b0111;
   #5 {A, B, C, D} = 4'b1000;
   #5 {A, B, C, D} = 4'b1001;
   #5 {A, B, C, D} = 4'b1010;
   #5 {A, B, C, D} = 4'b1011;
   #5 {A, B, C, D} = 4'b1100;
   #5 {A, B, C, D} = 4'b1101;
   #5 {A, B, C, D} = 4'b1110;
   #5 {A, B, C, D} = 4'b1111;
 end
 initial begin
   #100 $finish;
 end

endmodule

HW-271/problem_2.vcd
$date
    Mar  3, 2015  21:16:51
$end
$version
    TOOL:	ncsim	14.10-p001
$end
$timescale
    1 ns
$end

$scope module t_Problem_2 $end
$var reg       1 !    A  $end
$var reg       1 "    B  $end
$var reg       1 #    C  $end
$var reg       1 $    D  $end
$var wire      1 %    Y1  $end
$var wire      1 &    Y2  $end

$scope module M0 $end
$var wire      1 %    Y1  $end
$var wire      1 &    Y2  $end
$var wire      1 '    A  $end
$var wire      1 (    B  $end
$var wire      1 )    C  $end
$var wire      1 *    D  $end
$var wire      1 +    A_not  $end
$var wire      1 ,    B_not  $end
$var wire      1 -    C_not  $end
$var wire      1 .    D_not  $end
$var wire      1 /    w4  $end
$var wire      1 0    w5  $end
$var wire      1 1    w6  $end
$var wire      1 2    w7  $end
$var wire      1 3    w11  $end
$var wire      1 4    w12  $end
$var wire      1 5    w13  $end
$var wire      1 6    w1  $end
$var wire      1 7    w2  $end
$upscope $end

$upscope $end

$enddefinitions $end
$dumpvars
x!
x"
x#
x$
x%
x&
x'
x(
x)
x*
x+
x,
x-
x.
x/
x0
x1
x2
x3
x4
x5
x6
x7
$end
#5
0$
0#
0"
0!
0'
0(
0)
0*
00
1.
1-
1+
0/
04
05
1,
03
02
01
0%
07
06
0&
#10
1$
1*
0.
16
1&
#15
0$
1#
1)
0*
1.
0-
17
06
#20
1$
1*
0.
07
0&
#25
0$
0#
1"
1(
0)
0*
1.
1-
1/
0,
1%
1&
#30
1$
1*
0.
0/
10
#35
0$
1#
1)
0*
1.
0-
00
11
0&
#40
1$
1*
0.
12
01
#45
0$
0#
0"
1!
1'
0(
0)
0*
1.
1-
0+
1,
02
0%
#50
1$
1*
0.
#55
0$
1#
1)
0*
1.
0-
#60
1$
1*
0.
13
1%
#65
0$
0#
1"
1(
0)
0*
14
1.
1-
0,
03
#70
1$
1*
0.
04
15
#75
0$
1#
1)
0*
1.
0-
05
0%
#80
1$
1*
0.
