HW-271/rca.v
module Add_rca (sum, c_out, a, b, c_in); output [15:0] sum;
output c_out;
input [15:0] a, b;
input c_in;
wire c_in4, c_in8, c_in12, c_out;
     Add_rca_4 M1 (sum[3:0],   c_in4,  a[3:0],   b[3:0],   c_in);
     Add_rca_4 M2 (sum[7:4],   c_in8,  a[7:4],   b[7:4],   c_in4);
     Add_rca_4 M3 (sum[11:8],  c_in12, a[11:8],  b[11:8],  c_in8);
     Add_rca_4 M4 (sum[15:12], c_out,  a[15:12], b[15:12], c_in12);
endmodule

module Add_rca_4 (sum, c_out, a, b, c_in); output [3: 0] sum;
output c_out;
input [3: 0] a, b;
input c_in;
wire c_in2, c_in3, c_in4;
     Add_full M1 (sum[0], c_in2,    a[0], b[0], c_in);
     Add_full M2 (sum[1], c_in3, a[1], b[1], c_in2);
     Add_full M3 (sum[2], c_in4, a[2], b[2], c_in3);
     Add_full M4 (sum[3], c_out, a[3], b[3], c_in4);
endmodule

module Add_full (sum, c_out, a, b, c_in); output sum, c_out;
input a, b, c_in;
wire w1, w2, w3;
Add_half M1 (w1, w2, a, b); Add_half M2 (sum, w3, w1, c_in); or M3 (c_out, w2, w3);
endmodule

module Add_half (sum, c_out, a, b); output sum, c_out;
input a, b;
xor M1 (sum, a, b);
and M2 (c_out, a, b); 
endmodule

module test_Add_rca ( );
  wire [15: 0] sum;
  wire         c_out;
  reg  [15: 0] a, b;
  reg          c_in;
  Add_rca M1 (sum, c_out, a, b, c_in);
  initial begin
    #100 $finish;
  end
  initial begin
  	#5 a = 0; b = 0; c_in = 0;
    #5 b = 5;
    #5 a = 50;
    #5 b = 100;
    #5 a = 200;
    #5 b = 500;
    #5 a = 1000;
    #5 b = 5000;
    #5 a = 10000;
    #5 b = 100000;
    #5 a = 200000;
    #5 b = 20;
	#5 a = 500000;
    #5 b = 500000;
  end
  initial begin
  	$dumpfile("rippleadder.vcd");
  	$dumpvars(0,test_Add_rca);
  end
endmodule

HW-271/rippleadder.vcd
$date
    Mar 17, 2015  18:54:02
$end
$version
    TOOL:	ncsim	14.10-p001
$end
$timescale
    1 ns
$end

$scope module test_Add_rca $end
$var wire      1 !    sum [15] $end
$var wire      1 "    sum [14] $end
$var wire      1 #    sum [13] $end
$var wire      1 $    sum [12] $end
$var wire      1 %    sum [11] $end
$var wire      1 &    sum [10] $end
$var wire      1 '    sum [9] $end
$var wire      1 (    sum [8] $end
$var wire      1 )    sum [7] $end
$var wire      1 *    sum [6] $end
$var wire      1 +    sum [5] $end
$var wire      1 ,    sum [4] $end
$var wire      1 -    sum [3] $end
$var wire      1 .    sum [2] $end
$var wire      1 /    sum [1] $end
$var wire      1 0    sum [0] $end
$var wire      1 1    c_out  $end
$var reg      16 2    a [15:0] $end
$var reg      16 3    b [15:0] $end
$var reg       1 4    c_in  $end

$scope module M1 $end
$var wire      1 !    sum [15] $end
$var wire      1 "    sum [14] $end
$var wire      1 #    sum [13] $end
$var wire      1 $    sum [12] $end
$var wire      1 %    sum [11] $end
$var wire      1 &    sum [10] $end
$var wire      1 '    sum [9] $end
$var wire      1 (    sum [8] $end
$var wire      1 )    sum [7] $end
$var wire      1 *    sum [6] $end
$var wire      1 +    sum [5] $end
$var wire      1 ,    sum [4] $end
$var wire      1 -    sum [3] $end
$var wire      1 .    sum [2] $end
$var wire      1 /    sum [1] $end
$var wire      1 0    sum [0] $end
$var wire      1 1    c_out  $end
$var wire      1 5    a [15] $end
$var wire      1 6    a [14] $end
$var wire      1 7    a [13] $end
$var wire      1 8    a [12] $end
$var wire      1 9    a [11] $end
$var wire      1 :    a [10] $end
$var wire      1 ;    a [9] $end
$var wire      1 <    a [8] $end
$var wire      1 =    a [7] $end
$var wire      1 >    a [6] $end
$var wire      1 ?    a [5] $end
$var wire      1 @    a [4] $end
$var wire      1 A    a [3] $end
$var wire      1 B    a [2] $end
$var wire      1 C    a [1] $end
$var wire      1 D    a [0] $end
$var wire      1 E    b [15] $end
$var wire      1 F    b [14] $end
$var wire      1 G    b [13] $end
$var wire      1 H    b [12] $end
$var wire      1 I    b [11] $end
$var wire      1 J    b [10] $end
$var wire      1 K    b [9] $end
$var wire      1 L    b [8] $end
$var wire      1 M    b [7] $end
$var wire      1 N    b [6] $end
$var wire      1 O    b [5] $end
$var wire      1 P    b [4] $end
$var wire      1 Q    b [3] $end
$var wire      1 R    b [2] $end
$var wire      1 S    b [1] $end
$var wire      1 T    b [0] $end
$var wire      1 U    c_in  $end
$var wire      1 V    c_in4  $end
$var wire      1 W    c_in8  $end
$var wire      1 X    c_in12  $end

$scope module M1 $end
$var wire      1 -    sum [3] $end
$var wire      1 .    sum [2] $end
$var wire      1 /    sum [1] $end
$var wire      1 0    sum [0] $end
$var wire      1 V    c_out  $end
$var wire      1 A    a [3] $end
$var wire      1 B    a [2] $end
$var wire      1 C    a [1] $end
$var wire      1 D    a [0] $end
$var wire      1 Q    b [3] $end
$var wire      1 R    b [2] $end
$var wire      1 S    b [1] $end
$var wire      1 T    b [0] $end
$var wire      1 U    c_in  $end
$var wire      1 Y    c_in2  $end
$var wire      1 Z    c_in3  $end
$var wire      1 [    c_in4  $end

$scope module M1 $end
$var wire      1 0    sum  $end
$var wire      1 Y    c_out  $end
$var wire      1 D    a  $end
$var wire      1 T    b  $end
$var wire      1 U    c_in  $end
$var wire      1 \    w1  $end
$var wire      1 ]    w2  $end
$var wire      1 ^    w3  $end

$scope module M1 $end
$var wire      1 \    sum  $end
$var wire      1 ]    c_out  $end
$var wire      1 D    a  $end
$var wire      1 T    b  $end
$upscope $end


$scope module M2 $end
$var wire      1 0    sum  $end
$var wire      1 ^    c_out  $end
$var wire      1 \    a  $end
$var wire      1 U    b  $end
$upscope $end

$upscope $end


$scope module M2 $end
$var wire      1 /    sum  $end
$var wire      1 Z    c_out  $end
$var wire      1 C    a  $end
$var wire      1 S    b  $end
$var wire      1 Y    c_in  $end
$var wire      1 _    w1  $end
$var wire      1 `    w2  $end
$var wire      1 a    w3  $end

$scope module M1 $end
$var wire      1 _    sum  $end
$var wire      1 `    c_out  $end
$var wire      1 C    a  $end
$var wire      1 S    b  $end
$upscope $end


$scope module M2 $end
$var wire      1 /    sum  $end
$var wire      1 a    c_out  $end
$var wire      1 _    a  $end
$var wire      1 Y    b  $end
$upscope $end

$upscope $end


$scope module M3 $end
$var wire      1 .    sum  $end
$var wire      1 [    c_out  $end
$var wire      1 B    a  $end
$var wire      1 R    b  $end
$var wire      1 Z    c_in  $end
$var wire      1 b    w1  $end
$var wire      1 c    w2  $end
$var wire      1 d    w3  $end

$scope module M1 $end
$var wire      1 b    sum  $end
$var wire      1 c    c_out  $end
$var wire      1 B    a  $end
$var wire      1 R    b  $end
$upscope $end


$scope module M2 $end
$var wire      1 .    sum  $end
$var wire      1 d    c_out  $end
$var wire      1 b    a  $end
$var wire      1 Z    b  $end
$upscope $end

$upscope $end


$scope module M4 $end
$var wire      1 -    sum  $end
$var wire      1 V    c_out  $end
$var wire      1 A    a  $end
$var wire      1 Q    b  $end
$var wire      1 [    c_in  $end
$var wire      1 e    w1  $end
$var wire      1 f    w2  $end
$var wire      1 g    w3  $end

$scope module M1 $end
$var wire      1 e    sum  $end
$var wire      1 f    c_out  $end
$var wire      1 A    a  $end
$var wire      1 Q    b  $end
$upscope $end


$scope module M2 $end
$var wire      1 -    sum  $end
$var wire      1 g    c_out  $end
$var wire      1 e    a  $end
$var wire      1 [    b  $end
$upscope $end

$upscope $end

$upscope $end


$scope module M2 $end
$var wire      1 )    sum [3] $end
$var wire      1 *    sum [2] $end
$var wire      1 +    sum [1] $end
$var wire      1 ,    sum [0] $end
$var wire      1 W    c_out  $end
$var wire      1 =    a [3] $end
$var wire      1 >    a [2] $end
$var wire      1 ?    a [1] $end
$var wire      1 @    a [0] $end
$var wire      1 M    b [3] $end
$var wire      1 N    b [2] $end
$var wire      1 O    b [1] $end
$var wire      1 P    b [0] $end
$var wire      1 V    c_in  $end
$var wire      1 h    c_in2  $end
$var wire      1 i    c_in3  $end
$var wire      1 j    c_in4  $end

$scope module M1 $end
$var wire      1 ,    sum  $end
$var wire      1 h    c_out  $end
$var wire      1 @    a  $end
$var wire      1 P    b  $end
$var wire      1 V    c_in  $end
$var wire      1 k    w1  $end
$var wire      1 l    w2  $end
$var wire      1 m    w3  $end

$scope module M1 $end
$var wire      1 k    sum  $end
$var wire      1 l    c_out  $end
$var wire      1 @    a  $end
$var wire      1 P    b  $end
$upscope $end


$scope module M2 $end
$var wire      1 ,    sum  $end
$var wire      1 m    c_out  $end
$var wire      1 k    a  $end
$var wire      1 V    b  $end
$upscope $end

$upscope $end


$scope module M2 $end
$var wire      1 +    sum  $end
$var wire      1 i    c_out  $end
$var wire      1 ?    a  $end
$var wire      1 O    b  $end
$var wire      1 h    c_in  $end
$var wire      1 n    w1  $end
$var wire      1 o    w2  $end
$var wire      1 p    w3  $end

$scope module M1 $end
$var wire      1 n    sum  $end
$var wire      1 o    c_out  $end
$var wire      1 ?    a  $end
$var wire      1 O    b  $end
$upscope $end


$scope module M2 $end
$var wire      1 +    sum  $end
$var wire      1 p    c_out  $end
$var wire      1 n    a  $end
$var wire      1 h    b  $end
$upscope $end

$upscope $end


$scope module M3 $end
$var wire      1 *    sum  $end
$var wire      1 j    c_out  $end
$var wire      1 >    a  $end
$var wire      1 N    b  $end
$var wire      1 i    c_in  $end
$var wire      1 q    w1  $end
$var wire      1 r    w2  $end
$var wire      1 s    w3  $end

$scope module M1 $end
$var wire      1 q    sum  $end
$var wire      1 r    c_out  $end
$var wire      1 >    a  $end
$var wire      1 N    b  $end
$upscope $end


$scope module M2 $end
$var wire      1 *    sum  $end
$var wire      1 s    c_out  $end
$var wire      1 q    a  $end
$var wire      1 i    b  $end
$upscope $end

$upscope $end


$scope module M4 $end
$var wire      1 )    sum  $end
$var wire      1 W    c_out  $end
$var wire      1 =    a  $end
$var wire      1 M    b  $end
$var wire      1 j    c_in  $end
$var wire      1 t    w1  $end
$var wire      1 u    w2  $end
$var wire      1 v    w3  $end

$scope module M1 $end
$var wire      1 t    sum  $end
$var wire      1 u    c_out  $end
$var wire      1 =    a  $end
$var wire      1 M    b  $end
$upscope $end


$scope module M2 $end
$var wire      1 )    sum  $end
$var wire      1 v    c_out  $end
$var wire      1 t    a  $end
$var wire      1 j    b  $end
$upscope $end

$upscope $end

$upscope $end


$scope module M3 $end
$var wire      1 %    sum [3] $end
$var wire      1 &    sum [2] $end
$var wire      1 '    sum [1] $end
$var wire      1 (    sum [0] $end
$var wire      1 X    c_out  $end
$var wire      1 9    a [3] $end
$var wire      1 :    a [2] $end
$var wire      1 ;    a [1] $end
$var wire      1 <    a [0] $end
$var wire      1 I    b [3] $end
$var wire      1 J    b [2] $end
$var wire      1 K    b [1] $end
$var wire      1 L    b [0] $end
$var wire      1 W    c_in  $end
$var wire      1 w    c_in2  $end
$var wire      1 x    c_in3  $end
$var wire      1 y    c_in4  $end

$scope module M1 $end
$var wire      1 (    sum  $end
$var wire      1 w    c_out  $end
$var wire      1 <    a  $end
$var wire      1 L    b  $end
$var wire      1 W    c_in  $end
$var wire      1 z    w1  $end
$var wire      1 {    w2  $end
$var wire      1 |    w3  $end

$scope module M1 $end
$var wire      1 z    sum  $end
$var wire      1 {    c_out  $end
$var wire      1 <    a  $end
$var wire      1 L    b  $end
$upscope $end


$scope module M2 $end
$var wire      1 (    sum  $end
$var wire      1 |    c_out  $end
$var wire      1 z    a  $end
$var wire      1 W    b  $end
$upscope $end

$upscope $end


$scope module M2 $end
$var wire      1 '    sum  $end
$var wire      1 x    c_out  $end
$var wire      1 ;    a  $end
$var wire      1 K    b  $end
$var wire      1 w    c_in  $end
$var wire      1 }    w1  $end
$var wire      1 ~    w2  $end
$var wire      1 !!   w3  $end

$scope module M1 $end
$var wire      1 }    sum  $end
$var wire      1 ~    c_out  $end
$var wire      1 ;    a  $end
$var wire      1 K    b  $end
$upscope $end


$scope module M2 $end
$var wire      1 '    sum  $end
$var wire      1 !!   c_out  $end
$var wire      1 }    a  $end
$var wire      1 w    b  $end
$upscope $end

$upscope $end


$scope module M3 $end
$var wire      1 &    sum  $end
$var wire      1 y    c_out  $end
$var wire      1 :    a  $end
$var wire      1 J    b  $end
$var wire      1 x    c_in  $end
$var wire      1 "!   w1  $end
$var wire      1 #!   w2  $end
$var wire      1 $!   w3  $end

$scope module M1 $end
$var wire      1 "!   sum  $end
$var wire      1 #!   c_out  $end
$var wire      1 :    a  $end
$var wire      1 J    b  $end
$upscope $end


$scope module M2 $end
$var wire      1 &    sum  $end
$var wire      1 $!   c_out  $end
$var wire      1 "!   a  $end
$var wire      1 x    b  $end
$upscope $end

$upscope $end


$scope module M4 $end
$var wire      1 %    sum  $end
$var wire      1 X    c_out  $end
$var wire      1 9    a  $end
$var wire      1 I    b  $end
$var wire      1 y    c_in  $end
$var wire      1 %!   w1  $end
$var wire      1 &!   w2  $end
$var wire      1 '!   w3  $end

$scope module M1 $end
$var wire      1 %!   sum  $end
$var wire      1 &!   c_out  $end
$var wire      1 9    a  $end
$var wire      1 I    b  $end
$upscope $end


$scope module M2 $end
$var wire      1 %    sum  $end
$var wire      1 '!   c_out  $end
$var wire      1 %!   a  $end
$var wire      1 y    b  $end
$upscope $end

$upscope $end

$upscope $end


$scope module M4 $end
$var wire      1 !    sum [3] $end
$var wire      1 "    sum [2] $end
$var wire      1 #    sum [1] $end
$var wire      1 $    sum [0] $end
$var wire      1 1    c_out  $end
$var wire      1 5    a [3] $end
$var wire      1 6    a [2] $end
$var wire      1 7    a [1] $end
$var wire      1 8    a [0] $end
$var wire      1 E    b [3] $end
$var wire      1 F    b [2] $end
$var wire      1 G    b [1] $end
$var wire      1 H    b [0] $end
$var wire      1 X    c_in  $end
$var wire      1 (!   c_in2  $end
$var wire      1 )!   c_in3  $end
$var wire      1 *!   c_in4  $end

$scope module M1 $end
$var wire      1 $    sum  $end
$var wire      1 (!   c_out  $end
$var wire      1 8    a  $end
$var wire      1 H    b  $end
$var wire      1 X    c_in  $end
$var wire      1 +!   w1  $end
$var wire      1 ,!   w2  $end
$var wire      1 -!   w3  $end

$scope module M1 $end
$var wire      1 +!   sum  $end
$var wire      1 ,!   c_out  $end
$var wire      1 8    a  $end
$var wire      1 H    b  $end
$upscope $end


$scope module M2 $end
$var wire      1 $    sum  $end
$var wire      1 -!   c_out  $end
$var wire      1 +!   a  $end
$var wire      1 X    b  $end
$upscope $end

$upscope $end


$scope module M2 $end
$var wire      1 #    sum  $end
$var wire      1 )!   c_out  $end
$var wire      1 7    a  $end
$var wire      1 G    b  $end
$var wire      1 (!   c_in  $end
$var wire      1 .!   w1  $end
$var wire      1 /!   w2  $end
$var wire      1 0!   w3  $end

$scope module M1 $end
$var wire      1 .!   sum  $end
$var wire      1 /!   c_out  $end
$var wire      1 7    a  $end
$var wire      1 G    b  $end
$upscope $end


$scope module M2 $end
$var wire      1 #    sum  $end
$var wire      1 0!   c_out  $end
$var wire      1 .!   a  $end
$var wire      1 (!   b  $end
$upscope $end

$upscope $end


$scope module M3 $end
$var wire      1 "    sum  $end
$var wire      1 *!   c_out  $end
$var wire      1 6    a  $end
$var wire      1 F    b  $end
$var wire      1 )!   c_in  $end
$var wire      1 1!   w1  $end
$var wire      1 2!   w2  $end
$var wire      1 3!   w3  $end

$scope module M1 $end
$var wire      1 1!   sum  $end
$var wire      1 2!   c_out  $end
$var wire      1 6    a  $end
$var wire      1 F    b  $end
$upscope $end


$scope module M2 $end
$var wire      1 "    sum  $end
$var wire      1 3!   c_out  $end
$var wire      1 1!   a  $end
$var wire      1 )!   b  $end
$upscope $end

$upscope $end


$scope module M4 $end
$var wire      1 !    sum  $end
$var wire      1 1    c_out  $end
$var wire      1 5    a  $end
$var wire      1 E    b  $end
$var wire      1 *!   c_in  $end
$var wire      1 4!   w1  $end
$var wire      1 5!   w2  $end
$var wire      1 6!   w3  $end

$scope module M1 $end
$var wire      1 4!   sum  $end
$var wire      1 5!   c_out  $end
$var wire      1 5    a  $end
$var wire      1 E    b  $end
$upscope $end


$scope module M2 $end
$var wire      1 !    sum  $end
$var wire      1 6!   c_out  $end
$var wire      1 4!   a  $end
$var wire      1 *!   b  $end
$upscope $end

$upscope $end

$upscope $end

$upscope $end

$upscope $end

$enddefinitions $end
$dumpvars
x!
x"
x#
x$
x%
x&
x'
x(
x)
x*
x+
x,
x-
x.
x/
x0
x1
bx 2
bx 3
x4
x5
x6
x7
x8
x9
x:
x;
x<
x=
x>
x?
x@
xA
xB
xC
xD
xE
xF
xG
xH
xI
xJ
xK
xL
xM
xN
xO
xP
xQ
xR
xS
xT
xU
xV
xW
xX
xY
xZ
x[
x\
x]
x^
x_
x`
xa
xb
xc
xd
xe
xf
xg
xh
xi
xj
xk
xl
xm
xn
xo
xp
xq
xr
xs
xt
xu
xv
xw
xx
xy
xz
x{
x|
x}
x~
x!!
x"!
x#!
x$!
x%!
x&!
x'!
x(!
x)!
x*!
x+!
x,!
x-!
x.!
x/!
x0!
x1!
x2!
x3!
x4!
x5!
x6!
$end
#5
b0 2
b0 3
04
0U
0E
0F
0G
0H
0I
0J
0K
0L
0M
0N
0O
0P
0Q
0R
0S
0T
05
06
07
08
09
0:
0;
0<
0=
0>
0?
0@
0A
0B
0C
0D
0\
0_
0b
0e
0k
0n
0q
0t
0z
0}
0"!
0%!
0+!
0.!
01!
04!
0]
0`
0c
0f
0l
0o
0r
0u
0{
0~
0#!
0&!
0,!
0/!
02!
05!
0^
0Y
06!
03!
00!
0-!
0'!
0$!
0!!
0|
0v
0s
0p
0m
0g
0d
0a
00
0Z
0[
0V
0h
0i
0j
0W
0w
0x
0y
0X
0(!
0)!
0*!
01
0/
0!
0"
0#
0$
0%
0&
0'
0(
0)
0*
0+
0,
0-
0.
#10
b101 3
1R
1T
1\
1b
1.
10
#15
b110010 2
1?
1@
1C
1_
1k
1n
1+
1,
1/
#20
b1100100 3
1N
1O
0T
0\
0n
1o
1q
0*
1i
0+
00
1s
1j
1)
#25
b11001000 2
1=
1>
0?
0@
1A
0C
0_
1e
0k
1n
0o
0q
1r
1t
0)
1v
0*
0s
0i
1+
0,
1-
0/
1W
1(
#30
b111110100 3
1L
1M
1P
1k
0t
1u
1z
0(
1|
1)
0v
1,
1w
1'
#35
b1111101000 2
1;
1<
1?
0n
1o
0z
1{
1}
0'
1!!
1(
0|
1i
0+
1*
1x
1&
#40
b1001110001000 3
1H
1K
0N
0O
0P
1Q
0R
0b
0e
1f
0k
1n
0o
1q
0r
0}
1~
1+!
1$
1'
0!!
0j
1*
0s
0i
1+
1,
1V
0-
0.
0)
#45
b10011100010000 2
17
1:
0=
0>
0?
1@
0A
1e
0f
1k
0n
0q
1t
0u
1"!
1.!
1#
0&
1$!
0W
1)
0*
0+
1,
0m
0V
1-
0(
1y
1%
#50
b1000011010100000 3
1E
0H
1J
0L
1O
0Q
0e
1n
1z
0{
0"!
1#!
0+!
14!
1!
0$
1&
0$!
0w
1(
1+
0-
0'
#55
b110101000000 2
07
19
0;
1>
0@
0k
1q
1}
0~
1%!
0.!
0#
0%
1'!
0x
1'
1*
0,
0&
1X
1$
#60
b10100 3
0E
0J
0K
0M
0O
1P
1R
1b
1k
0n
0t
0}
1"!
0#!
04!
0!
0y
1&
0'
0)
0+
1,
1.
1%
0'!
0X
0$
#65
b1010000100100000 2
15
17
09
0:
0>
1?
1n
0q
0"!
0%!
1.!
14!
1!
1#
0%
0&
0*
1+
#70
b1010000100100000 3
1E
1G
1L
1O
0P
0R
0b
0k
0n
1o
0z
1{
0.!
1/!
04!
15!
11
0!
1)!
0#
1w
0(
1i
0+
0,
0.
1*
1'
1"
