project-287/sqrt64.v
module sqrt64(clk, rdy, reset, x, acc);
   input  clk;
   output rdy;
   input  reset;

   input [63:0] x;
   output [31:0] acc;


   // acc holds the accumulated result, and acc2 is the accumulated
   // square of the accumulated result.
   reg [31:0] acc;
   reg [63:0] acc2;

   // Keep track of which bit I'm working on.
   reg [5:0]  bitl;
   reg [31:0] bitm;
   //assign bitm = 1 << bitl;
   reg [63:0] bit2;
   //assign bit2 = 1 << (bitl << 1);

   // The output is ready when the bitl counter underflows.
   reg rdy;
   //assign rdy = bitl[5];

   // guess holds the potential next values for acc, and guess2 holds
   // the square of that guess. The guess2 calculation is a little bit
   // subtle. The idea is that:
   //
   //      guess2 = (acc + bit) * (acc + bit)
   //             = (acc * acc) + 2*acc*bit + bit*bit
   //             = acc2 + 2*acc*bit + bit2
   //             = acc2 + 2 * (acc<<bitl) + bit
   //
   // This works out using shifts because bit and bit2 are known to
   // have only a single bit in them.
   reg [31:0] guess;
   //assign guess = acc | bitm;
   reg [63:0] guess2;
   //assign guess2 = acc2 + bit2 + ((acc << bitl) << 1);

   always @(*)
   begin
      bitm = 1 << bitl;
      bit2 = 1 << (bitl << 1);
      rdy = bitl[5];
      guess = acc | bitm;
      guess2 = acc2 + bit2 + ((acc << bitl) << 1);
   end

   always @(posedge reset or posedge clk)
   begin
      if (reset) begin
       acc <= 0;
       acc2 <= 0;
       bitl <= 31;
      end
      else begin
	     if (guess2 <= x) begin
	        acc  <= guess;
	        acc2 <= guess2;
	     end
	     bitl <= bitl - 1;
      end
   end
endmodule

/////////////////////////
//Testbench for sqrt64 //
/////////////////////////

module main;
   reg clk, reset;
   reg [63:0] value;
   wire [31:0] result;
   wire rdy;
   sqrt64 root(.clk(clk), .rdy(rdy), .reset(reset), .x(value), .acc(result));
   always #4 clk = ~clk;
   always @(posedge rdy) begin
      $display("sqrt(%d) --> %d", value, result);
      $finish;
   end
initial begin
$dumpfile("sqrt64dump.vcd");
$dumpvars(0, main);
end
   initial begin
      clk = 0;
      reset = 1;
      $monitor($time,,"%m.acc = %b", root.acc);
      #100 value =64'd1231231231314096;
      reset = 0;
   end
endmodule /* main */

project-287/sqrt64dump.vcd
$date
	Tue Apr  7 18:10:33 2015
$end

$version
	Synopsys VCS version I-2014.03-2
$end

$timescale
	1s
$end

$comment Csum: 1 b6916064051f48e6 $end


$scope module main $end
$var reg 1 ! clk $end
$var reg 1 " reset $end
$var reg 64 # value [63:0] $end
$var wire 1 $ result [31] $end
$var wire 1 % result [30] $end
$var wire 1 & result [29] $end
$var wire 1 ' result [28] $end
$var wire 1 ( result [27] $end
$var wire 1 ) result [26] $end
$var wire 1 * result [25] $end
$var wire 1 + result [24] $end
$var wire 1 , result [23] $end
$var wire 1 - result [22] $end
$var wire 1 . result [21] $end
$var wire 1 / result [20] $end
$var wire 1 0 result [19] $end
$var wire 1 1 result [18] $end
$var wire 1 2 result [17] $end
$var wire 1 3 result [16] $end
$var wire 1 4 result [15] $end
$var wire 1 5 result [14] $end
$var wire 1 6 result [13] $end
$var wire 1 7 result [12] $end
$var wire 1 8 result [11] $end
$var wire 1 9 result [10] $end
$var wire 1 : result [9] $end
$var wire 1 ; result [8] $end
$var wire 1 < result [7] $end
$var wire 1 = result [6] $end
$var wire 1 > result [5] $end
$var wire 1 ? result [4] $end
$var wire 1 @ result [3] $end
$var wire 1 A result [2] $end
$var wire 1 B result [1] $end
$var wire 1 C result [0] $end
$var wire 1 D rdy $end

$scope module root $end
$var reg 32 E acc [31:0] $end
$var wire 1 ! clk $end
$var reg 1 F rdy $end
$var wire 1 " reset $end
$var wire 64 # x [63:0] $end
$var reg 64 G acc2 [63:0] $end
$var reg 6 H bitl [5:0] $end
$var reg 32 I bitm [31:0] $end
$var reg 64 J bit2 [63:0] $end
$var reg 32 K guess [31:0] $end
$var reg 64 L guess2 [63:0] $end
$upscope $end

$upscope $end

$enddefinitions $end

#0
$dumpvars
0!
0D
1"
0C
09
08
07
06
05
04
03
02
01
00
0B
0/
0.
0-
0,
0+
0*
0)
0(
0'
0&
0A
0%
0$
0@
0?
0>
0=
0<
0;
0:
0F
b00000000000000000000000000000000 E
b0000000000000000000000000000000000000000000000000000000000000000 G
b0100000000000000000000000000000000000000000000000000000000000000 J
b011111 H
b10000000000000000000000000000000 I
b10000000000000000000000000000000 K
b0100000000000000000000000000000000000000000000000000000000000000 L
bxxxxxxxxxxxxxxxxxxxxxxxxxxxxxxxxxxxxxxxxxxxxxxxxxxxxxxxxxxxxxxxx #
$end
#4
1!
#8
0!
#12
1!
#16
0!
#20
1!
#24
0!
#28
1!
#32
0!
#36
1!
#40
0!
#44
1!
#48
0!
#52
1!
#56
0!
#60
1!
#64
0!
#68
1!
#72
0!
#76
1!
#80
0!
#84
1!
#88
0!
#92
1!
#96
0!
#100
b0000000000000100010111111100110001011100001011011100100010110000 #
0"
1!
b011110 H
b0001000000000000000000000000000000000000000000000000000000000000 L
b01000000000000000000000000000000 K
b0001000000000000000000000000000000000000000000000000000000000000 J
b01000000000000000000000000000000 I
#104
0!
#108
1!
b011101 H
b0000010000000000000000000000000000000000000000000000000000000000 L
b00100000000000000000000000000000 K
b0000010000000000000000000000000000000000000000000000000000000000 J
b00100000000000000000000000000000 I
#112
0!
#116
1!
b011100 H
b0000000100000000000000000000000000000000000000000000000000000000 L
b00010000000000000000000000000000 K
b0000000100000000000000000000000000000000000000000000000000000000 J
b00010000000000000000000000000000 I
#120
0!
#124
1!
b011011 H
b0000000001000000000000000000000000000000000000000000000000000000 L
b00001000000000000000000000000000 K
b0000000001000000000000000000000000000000000000000000000000000000 J
b00001000000000000000000000000000 I
#128
0!
#132
1!
b011010 H
b0000000000010000000000000000000000000000000000000000000000000000 L
b00000100000000000000000000000000 K
b0000000000010000000000000000000000000000000000000000000000000000 J
b00000100000000000000000000000000 I
#136
0!
#140
1!
b011001 H
b0000000000000100000000000000000000000000000000000000000000000000 L
b00000010000000000000000000000000 K
b0000000000000100000000000000000000000000000000000000000000000000 J
b00000010000000000000000000000000 I
#144
0!
#148
1!
b00000010000000000000000000000000 E
1*
b0000000000000100000000000000000000000000000000000000000000000000 G
b011000 H
b0000000000001001000000000000000000000000000000000000000000000000 L
b00000011000000000000000000000000 K
b0000000000000001000000000000000000000000000000000000000000000000 J
b00000001000000000000000000000000 I
#152
0!
#156
1!
b010111 H
b0000000000000110010000000000000000000000000000000000000000000000 L
b00000010100000000000000000000000 K
b0000000000000000010000000000000000000000000000000000000000000000 J
b00000000100000000000000000000000 I
#160
0!
#164
1!
b010110 H
b0000000000000101000100000000000000000000000000000000000000000000 L
b00000010010000000000000000000000 K
b0000000000000000000100000000000000000000000000000000000000000000 J
b00000000010000000000000000000000 I
#168
0!
#172
1!
b010101 H
b0000000000000100100001000000000000000000000000000000000000000000 L
b00000010001000000000000000000000 K
b0000000000000000000001000000000000000000000000000000000000000000 J
b00000000001000000000000000000000 I
#176
0!
#180
1!
b010100 H
b0000000000000100010000010000000000000000000000000000000000000000 L
b00000010000100000000000000000000 K
b0000000000000000000000010000000000000000000000000000000000000000 J
b00000000000100000000000000000000 I
#184
0!
#188
1!
b00000010000100000000000000000000 E
1/
b0000000000000100010000010000000000000000000000000000000000000000 G
b010011 H
b0000000000000100011000100100000000000000000000000000000000000000 L
b00000010000110000000000000000000 K
b0000000000000000000000000100000000000000000000000000000000000000 J
b00000000000010000000000000000000 I
#192
0!
#196
1!
b010010 H
b0000000000000100010100011001000000000000000000000000000000000000 L
b00000010000101000000000000000000 K
b0000000000000000000000000001000000000000000000000000000000000000 J
b00000000000001000000000000000000 I
#200
0!
#204
1!
b00000010000101000000000000000000 E
11
b0000000000000100010100011001000000000000000000000000000000000000 G
b010001 H
b0000000000000100010110011110010000000000000000000000000000000000 L
b00000010000101100000000000000000 K
b0000000000000000000000000000010000000000000000000000000000000000 J
b00000000000000100000000000000000 I
#208
0!
#212
1!
b00000010000101100000000000000000 E
12
b0000000000000100010110011110010000000000000000000000000000000000 G
b010000 H
b0000000000000100010111100001000100000000000000000000000000000000 L
b00000010000101110000000000000000 K
b0000000000000000000000000000000100000000000000000000000000000000 J
b00000000000000010000000000000000 I
#216
0!
#220
1!
b00000010000101110000000000000000 E
13
b0000000000000100010111100001000100000000000000000000000000000000 G
b001111 H
b0000000000000100011000000010100001000000000000000000000000000000 L
b00000010000101111000000000000000 K
b0000000000000000000000000000000001000000000000000000000000000000 J
b00000000000000001000000000000000 I
#224
0!
#228
1!
b001110 H
b0000000000000100010111110001110010010000000000000000000000000000 L
b00000010000101110100000000000000 K
b0000000000000000000000000000000000010000000000000000000000000000 J
b00000000000000000100000000000000 I
#232
0!
#236
1!
b00000010000101110100000000000000 E
15
b0000000000000100010111110001110010010000000000000000000000000000 G
b001101 H
b0000000000000100010111111010001001100100000000000000000000000000 L
b00000010000101110110000000000000 K
b0000000000000000000000000000000000000100000000000000000000000000 J
b00000000000000000010000000000000 I
#240
0!
#244
1!
b00000010000101110110000000000000 E
16
b0000000000000100010111111010001001100100000000000000000000000000 G
b001100 H
b0000000000000100010111111110010101010001000000000000000000000000 L
b00000010000101110111000000000000 K
b0000000000000000000000000000000000000001000000000000000000000000 J
b00000000000000000001000000000000 I
#248
0!
#252
1!
b001011 H
b0000000000000100010111111100001111011010010000000000000000000000 L
b00000010000101110110100000000000 K
b0000000000000000000000000000000000000000010000000000000000000000 J
b00000000000000000000100000000000 I
#256
0!
#260
1!
b00000010000101110110100000000000 E
18
b0000000000000100010111111100001111011010010000000000000000000000 G
b001010 H
b0000000000000100010111111101010010010101100100000000000000000000 L
b00000010000101110110110000000000 K
b0000000000000000000000000000000000000000000100000000000000000000 J
b00000000000000000000010000000000 I
#264
0!
#268
1!
b001001 H
b0000000000000100010111111100110000110111111001000000000000000000 L
b00000010000101110110101000000000 K
b0000000000000000000000000000000000000000000001000000000000000000 J
b00000000000000000000001000000000 I
#272
0!
#276
1!
b00000010000101110110101000000000 E
1:
b0000000000000100010111111100110000110111111001000000000000000000 G
b001000 H
b0000000000000100010111111101000001100110101110010000000000000000 L
b00000010000101110110101100000000 K
b0000000000000000000000000000000000000000000000010000000000000000 J
b00000000000000000000000100000000 I
#280
0!
#284
1!
b000111 H
b0000000000000100010111111100111001001111010011100100000000000000 L
b00000010000101110110101010000000 K
b0000000000000000000000000000000000000000000000000100000000000000 J
b00000000000000000000000010000000 I
#288
0!
#292
1!
b000110 H
b0000000000000100010111111100110101000011100110010001000000000000 L
b00000010000101110110101001000000 K
b0000000000000000000000000000000000000000000000000001000000000000 J
b00000000000000000000000001000000 I
#296
0!
#300
1!
b000101 H
b0000000000000100010111111100110010111101101111101000010000000000 L
b00000010000101110110101000100000 K
b0000000000000000000000000000000000000000000000000000010000000000 J
b00000000000000000000000000100000 I
#304
0!
#308
1!
b000100 H
b0000000000000100010111111100110001111010110100010100000100000000 L
b00000010000101110110101000010000 K
b0000000000000000000000000000000000000000000000000000000100000000 J
b00000000000000000000000000010000 I
#312
0!
#316
1!
b000011 H
b0000000000000100010111111100110001011001010110101010000001000000 L
b00000010000101110110101000001000 K
b0000000000000000000000000000000000000000000000000000000001000000 J
b00000000000000000000000000001000 I
#320
0!
#324
1!
b00000010000101110110101000001000 E
1@
b0000000000000100010111111100110001011001010110101010000001000000 G
b000010 H
b0000000000000100010111111100110001101010000101011111000010010000 L
b00000010000101110110101000001100 K
b0000000000000000000000000000000000000000000000000000000000010000 J
b00000000000000000000000000000100 I
#328
0!
#332
1!
b000001 H
b0000000000000100010111111100110001100001101110000100100001100100 L
b00000010000101110110101000001010 K
b0000000000000000000000000000000000000000000000000000000000000100 J
b00000000000000000000000000000010 I
#336
0!
#340
1!
b000000 H
b0000000000000100010111111100110001011101100010010111010001010001 L
b00000010000101110110101000001001 K
b0000000000000000000000000000000000000000000000000000000000000001 J
b00000000000000000000000000000001 I
#344
0!
#348
1!
b111111 H
b0100000000000100010111111100110001011001010110101010000001000000 L
b00000010000101110110101000001000 K
1F
1D
b0100000000000000000000000000000000000000000000000000000000000000 J
b00000000000000000000000000000000 I
