project-287/sqrt64.v
module sqrt64(clk, rdy, reset, x, .y(acc));
   input  clk;
   output rdy;
   input  reset;

   input [63:0] x;
   output [31:0] acc;


   // acc holds the accumulated result, and acc2 is the accumulated
   // square of the accumulated result.
   reg [31:0] acc;
   reg [63:0] acc2;

   // Keep track of which bit I'm working on.
   reg [5:0]  bitl;
   wire [31:0] bitm;
   assign bitm = 1 << bitl;
   wire [63:0] bit2;
   assign bit2 = 1 << (bitl << 1);

   // The output is ready when the bitl counter underflows.
   wire rdy = bitl[5];

   // guess holds the potential next values for acc, and guess2 holds
   // the square of that guess. The guess2 calculation is a little bit
   // subtle. The idea is that:
   //
   //      guess2 = (acc + bit) * (acc + bit)
   //             = (acc * acc) + 2*acc*bit + bit*bit
   //             = acc2 + 2*acc*bit + bit2
   //             = acc2 + 2 * (acc<<bitl) + bit
   //
   // This works out using shifts because bit and bit2 are known to
   // have only a single bit in them.
   wire [31:0] guess;
   assign guess = acc | bitm;
   wire [63:0] guess2;
   assign guess2 = acc2 + bit2 + ((acc << bitl) << 1);

   task clear;
      begin
	 acc = 0;
	 acc2 = 0;
	 bitl = 31;
      end
   endtask

   initial clear;

   always @(reset or posedge clk)
      if (reset)
       clear;
      else begin
	 if (guess2 <= x) begin
	    acc  <= guess;
	    acc2 <= guess2;
	 end
	 bitl <= bitl - 1;
      end

endmodule

module main;

   reg clk, reset;
   reg [63:0] value;
   wire [31:0] result;
   wire rdy;

   sqrt64 root(.clk(clk), .rdy(rdy), .reset(reset), .x(value), .y(result));

   always #4 clk = ~clk;

   always @(posedge rdy) begin
      $display("sqrt(%d) --> %d", value, result);
      $finish;
   end
initial begin
$dumpfile("sqrt64dump.vcd");
$dumpvars(0, main);
end


   initial begin
      clk = 0;
      reset = 1;
      $monitor($time,,"%m.acc = %b", root.acc);
      #100 value =64'd213213123244;
      reset = 0;
   end
endmodule /* main */

project-287/sqrt64dump.vcd
$date
	Tue Apr  7 16:23:08 2015
$end

$version
	Synopsys VCS version I-2014.03-2
$end

$timescale
	1s
$end

$comment Csum: 1 879065b9217c9652 $end


$scope module main $end
$var reg 1 ! clk $end
$var reg 1 " reset $end
$var reg 64 # value [63:0] $end
$var wire 1 $ result [31] $end
$var wire 1 % result [30] $end
$var wire 1 & result [29] $end
$var wire 1 ' result [28] $end
$var wire 1 ( result [27] $end
$var wire 1 ) result [26] $end
$var wire 1 * result [25] $end
$var wire 1 + result [24] $end
$var wire 1 , result [23] $end
$var wire 1 - result [22] $end
$var wire 1 . result [21] $end
$var wire 1 / result [20] $end
$var wire 1 0 result [19] $end
$var wire 1 1 result [18] $end
$var wire 1 2 result [17] $end
$var wire 1 3 result [16] $end
$var wire 1 4 result [15] $end
$var wire 1 5 result [14] $end
$var wire 1 6 result [13] $end
$var wire 1 7 result [12] $end
$var wire 1 8 result [11] $end
$var wire 1 9 result [10] $end
$var wire 1 : result [9] $end
$var wire 1 ; result [8] $end
$var wire 1 < result [7] $end
$var wire 1 = result [6] $end
$var wire 1 > result [5] $end
$var wire 1 ? result [4] $end
$var wire 1 @ result [3] $end
$var wire 1 A result [2] $end
$var wire 1 B result [1] $end
$var wire 1 C result [0] $end
$var wire 1 D rdy $end

$scope module root $end
$var reg 32 E acc [31:0] $end
$var wire 1 ! clk $end
$var wire 1 D rdy $end
$var wire 1 " reset $end
$var wire 64 # x [63:0] $end
$var reg 64 F acc2 [63:0] $end
$var reg 6 G bitl [5:0] $end
$var wire 32 H bitm [31:0] $end
$var wire 64 I bit2 [63:0] $end
$var wire 32 J guess [31:0] $end
$var wire 64 K guess2 [63:0] $end

$scope task clear $end
$upscope $end

$upscope $end

$upscope $end

$enddefinitions $end

#0
$dumpvars
0!
0D
1"
0C
09
08
07
06
05
04
03
02
01
00
0B
0/
0.
0-
0,
0+
0*
0)
0(
0'
0&
0A
0%
0$
0@
0?
0>
0=
0<
0;
0:
b00000000000000000000000000000000 E
b0000000000000000000000000000000000000000000000000000000000000000 F
b0100000000000000000000000000000000000000000000000000000000000000 I
b011111 G
b10000000000000000000000000000000 H
b10000000000000000000000000000000 J
b0100000000000000000000000000000000000000000000000000000000000000 K
bxxxxxxxxxxxxxxxxxxxxxxxxxxxxxxxxxxxxxxxxxxxxxxxxxxxxxxxxxxxxxxxx #
$end
#4
1!
#8
0!
#12
1!
#16
0!
#20
1!
#24
0!
#28
1!
#32
0!
#36
1!
#40
0!
#44
1!
#48
0!
#52
1!
#56
0!
#60
1!
#64
0!
#68
1!
#72
0!
#76
1!
#80
0!
#84
1!
#88
0!
#92
1!
#96
0!
#100
b0000000000000000000000000011000110100100011111100001001010101100 #
0"
1!
b011110 G
b0001000000000000000000000000000000000000000000000000000000000000 I
b01000000000000000000000000000000 H
b01000000000000000000000000000000 J
b0001000000000000000000000000000000000000000000000000000000000000 K
#104
0!
#108
1!
b011101 G
b0000010000000000000000000000000000000000000000000000000000000000 I
b00100000000000000000000000000000 H
b00100000000000000000000000000000 J
b0000010000000000000000000000000000000000000000000000000000000000 K
#112
0!
#116
1!
b011100 G
b0000000100000000000000000000000000000000000000000000000000000000 I
b00010000000000000000000000000000 H
b00010000000000000000000000000000 J
b0000000100000000000000000000000000000000000000000000000000000000 K
#120
0!
#124
1!
b011011 G
b0000000001000000000000000000000000000000000000000000000000000000 I
b00001000000000000000000000000000 H
b00001000000000000000000000000000 J
b0000000001000000000000000000000000000000000000000000000000000000 K
#128
0!
#132
1!
b011010 G
b0000000000010000000000000000000000000000000000000000000000000000 I
b00000100000000000000000000000000 H
b00000100000000000000000000000000 J
b0000000000010000000000000000000000000000000000000000000000000000 K
#136
0!
#140
1!
b011001 G
b0000000000000100000000000000000000000000000000000000000000000000 I
b00000010000000000000000000000000 H
b00000010000000000000000000000000 J
b0000000000000100000000000000000000000000000000000000000000000000 K
#144
0!
#148
1!
b011000 G
b0000000000000001000000000000000000000000000000000000000000000000 I
b00000001000000000000000000000000 H
b00000001000000000000000000000000 J
b0000000000000001000000000000000000000000000000000000000000000000 K
#152
0!
#156
1!
b010111 G
b0000000000000000010000000000000000000000000000000000000000000000 I
b00000000100000000000000000000000 H
b00000000100000000000000000000000 J
b0000000000000000010000000000000000000000000000000000000000000000 K
#160
0!
#164
1!
b010110 G
b0000000000000000000100000000000000000000000000000000000000000000 I
b00000000010000000000000000000000 H
b00000000010000000000000000000000 J
b0000000000000000000100000000000000000000000000000000000000000000 K
#168
0!
#172
1!
b010101 G
b0000000000000000000001000000000000000000000000000000000000000000 I
b00000000001000000000000000000000 H
b00000000001000000000000000000000 J
b0000000000000000000001000000000000000000000000000000000000000000 K
#176
0!
#180
1!
b010100 G
b0000000000000000000000010000000000000000000000000000000000000000 I
b00000000000100000000000000000000 H
b00000000000100000000000000000000 J
b0000000000000000000000010000000000000000000000000000000000000000 K
#184
0!
#188
1!
b010011 G
b0000000000000000000000000100000000000000000000000000000000000000 I
b00000000000010000000000000000000 H
b00000000000010000000000000000000 J
b0000000000000000000000000100000000000000000000000000000000000000 K
#192
0!
#196
1!
b010010 G
b0000000000000000000000000001000000000000000000000000000000000000 I
b00000000000001000000000000000000 H
b00000000000001000000000000000000 J
b0000000000000000000000000001000000000000000000000000000000000000 K
#200
0!
#204
1!
b00000000000001000000000000000000 E
11
b0000000000000000000000000001000000000000000000000000000000000000 F
b010001 G
b0000000000000000000000000000010000000000000000000000000000000000 I
b00000000000000100000000000000000 H
b00000000000001100000000000000000 J
b0000000000000000000000000010010000000000000000000000000000000000 K
#208
0!
#212
1!
b00000000000001100000000000000000 E
12
b0000000000000000000000000010010000000000000000000000000000000000 F
b010000 G
b0000000000000000000000000000000100000000000000000000000000000000 I
b00000000000000010000000000000000 H
b00000000000001110000000000000000 J
b0000000000000000000000000011000100000000000000000000000000000000 K
#216
0!
#220
1!
b00000000000001110000000000000000 E
13
b0000000000000000000000000011000100000000000000000000000000000000 F
b001111 G
b0000000000000000000000000000000001000000000000000000000000000000 I
b00000000000000001000000000000000 H
b00000000000001111000000000000000 J
b0000000000000000000000000011100001000000000000000000000000000000 K
#224
0!
#228
1!
b001110 G
b0000000000000000000000000000000000010000000000000000000000000000 I
b00000000000000000100000000000000 H
b00000000000001110100000000000000 J
b0000000000000000000000000011010010010000000000000000000000000000 K
#232
0!
#236
1!
b001101 G
b0000000000000000000000000000000000000100000000000000000000000000 I
b00000000000000000010000000000000 H
b00000000000001110010000000000000 J
b0000000000000000000000000011001011000100000000000000000000000000 K
#240
0!
#244
1!
b001100 G
b0000000000000000000000000000000000000001000000000000000000000000 I
b00000000000000000001000000000000 H
b00000000000001110001000000000000 J
b0000000000000000000000000011000111100001000000000000000000000000 K
#248
0!
#252
1!
b001011 G
b0000000000000000000000000000000000000000010000000000000000000000 I
b00000000000000000000100000000000 H
b00000000000001110000100000000000 J
b0000000000000000000000000011000101110000010000000000000000000000 K
#256
0!
#260
1!
b00000000000001110000100000000000 E
18
b0000000000000000000000000011000101110000010000000000000000000000 F
b001010 G
b0000000000000000000000000000000000000000000100000000000000000000 I
b00000000000000000000010000000000 H
b00000000000001110000110000000000 J
b0000000000000000000000000011000110101000100100000000000000000000 K
#264
0!
#268
1!
b001001 G
b0000000000000000000000000000000000000000000001000000000000000000 I
b00000000000000000000001000000000 H
b00000000000001110000101000000000 J
b0000000000000000000000000011000110001100011001000000000000000000 K
#272
0!
#276
1!
b00000000000001110000101000000000 E
1:
b0000000000000000000000000011000110001100011001000000000000000000 F
b001000 G
b0000000000000000000000000000000000000000000000010000000000000000 I
b00000000000000000000000100000000 H
b00000000000001110000101100000000 J
b0000000000000000000000000011000110011010011110010000000000000000 K
#280
0!
#284
1!
b00000000000001110000101100000000 E
1;
b0000000000000000000000000011000110011010011110010000000000000000 F
b000111 G
b0000000000000000000000000000000000000000000000000100000000000000 I
b00000000000000000000000010000000 H
b00000000000001110000101110000000 J
b0000000000000000000000000011000110100001100001000100000000000000 K
#288
0!
#292
1!
b00000000000001110000101110000000 E
1<
b0000000000000000000000000011000110100001100001000100000000000000 F
b000110 G
b0000000000000000000000000000000000000000000000000001000000000000 I
b00000000000000000000000001000000 H
b00000000000001110000101111000000 J
b0000000000000000000000000011000110100101000010100001000000000000 K
#296
0!
#300
1!
b000101 G
b0000000000000000000000000000000000000000000000000000010000000000 I
b00000000000000000000000000100000 H
b00000000000001110000101110100000 J
b0000000000000000000000000011000110100011010001110010010000000000 K
#304
0!
#308
1!
b00000000000001110000101110100000 E
1>
b0000000000000000000000000011000110100011010001110010010000000000 F
b000100 G
b0000000000000000000000000000000000000000000000000000000100000000 I
b00000000000000000000000000010000 H
b00000000000001110000101110110000 J
b0000000000000000000000000011000110100100001010001001100100000000 K
#312
0!
#316
1!
b00000000000001110000101110110000 E
1?
b0000000000000000000000000011000110100100001010001001100100000000 F
b000011 G
b0000000000000000000000000000000000000000000000000000000001000000 I
b00000000000000000000000000001000 H
b00000000000001110000101110111000 J
b0000000000000000000000000011000110100100100110010101010001000000 K
#320
0!
#324
1!
b000010 G
b0000000000000000000000000000000000000000000000000000000000010000 I
b00000000000000000000000000000100 H
b00000000000001110000101110110100 J
b0000000000000000000000000011000110100100011000001111011010010000 K
#328
0!
#332
1!
b00000000000001110000101110110100 E
1A
b0000000000000000000000000011000110100100011000001111011010010000 F
b000001 G
b0000000000000000000000000000000000000000000000000000000000000100 I
b00000000000000000000000000000010 H
b00000000000001110000101110110110 J
b0000000000000000000000000011000110100100011111010010010101100100 K
#336
0!
#340
1!
b00000000000001110000101110110110 E
1B
b0000000000000000000000000011000110100100011111010010010101100100 F
b000000 G
b0000000000000000000000000000000000000000000000000000000000000001 I
b00000000000000000000000000000001 H
b00000000000001110000101110110111 J
b0000000000000000000000000011000110100100100010110011110011010001 K
#344
0!
#348
1!
b111111 G
b0100000000000000000000000000000000000000000000000000000000000000 I
b00000000000000000000000000000000 H
b00000000000001110000101110110110 J
1D
b0100000000000000000000000011000110100100011111010010010101100100 K
