project-287/sqrt64.v
/*
 * Copyright (c) 1999 Stephen Williams (steve@icarus.com)
 *
 *    This source code is free software; you can redistribute it
 *    and/or modify it in source code form under the terms of the GNU
 *    General Public License as published by the Free Software
 *    Foundation; either version 2 of the License, or (at your option)
 *    any later version.
 *
 *    This program is distributed in the hope that it will be useful,
 *    but WITHOUT ANY WARRANTY; without even the implied warranty of
 *    MERCHANTABILITY or FITNESS FOR A PARTICULAR PURPOSE.  See the
 *    GNU General Public License for more details.
 *
 *    You should have received a copy of the GNU General Public License
 *    along with this program; if not, write to the Free Software
 *    Foundation, Inc., 59 Temple Place - Suite 330, Boston, MA 02111-1307, USA
 *
 *   $Id: sqrt.vl,v 1.4 2004/10/04 01:10:56 steve Exp $"
 */

 /*
  * This example shows that Icarus Verilog can run non-trivial
  * programs, too. This uses a variety of Verilog language features
  * to implement the module of a square-root device. The program
  * uses IEEE1364-1995 language features and should work correctly
  * on any Verilog compiler.
  *
  * Run the file with Icarus Verilog under UNIX using the command:
  *
  *     % iverilog -osqrt sqrt.v
  *     % ./sqrt
  */

 /*
  * This module approximates the square root of an unsigned 32bit
  * number. The algorithm works by doing a bit-wise binary search.
  * Starting from the most significant bit, the accumulated value
  * tries to put a 1 in the bit position. If that makes the square
  * to big for the input, the bit is left zero, otherwise it is set
  * in the result. This continues for each bit, decreasing in
  * significance, until all the bits are calculated or all the
  * remaining bits are zero.
  *
  * Since the result is an integer, this function really calculates
  * value of the expression:
  *
  *      x = floor(sqrt(y))
  *
  * where sqrt(y) is the exact square root of y and floor(N) is the
  * largest integer <= N.
  *
  * For 32bit numbers, this will never run more then 16 iterations,
  * which amounts to 16 clocks.
  */

module sqrt32(clk, rdy, reset, x, .y(acc));
   input  clk;
   output rdy;
   input  reset;

   input [63:0] x;
   output [31:0] acc;


   // acc holds the accumulated result, and acc2 is the accumulated
   // square of the accumulated result.
   reg [31:0] acc;
   reg [63:0] acc2;

   // Keep track of which bit I'm working on.
   reg [5:0]  bitl;
   wire [31:0] bitm = 1 << bitl;
   wire [63:0] bit2 = 1 << (bitl << 1);

   // The output is ready when the bitl counter underflows.
   wire rdy = bitl[5];

   // guess holds the potential next values for acc, and guess2 holds
   // the square of that guess. The guess2 calculation is a little bit
   // subtle. The idea is that:
   //
   //      guess2 = (acc + bit) * (acc + bit)
   //             = (acc * acc) + 2*acc*bit + bit*bit
   //             = acc2 + 2*acc*bit + bit2
   //             = acc2 + 2 * (acc<<bitl) + bit
   //
   // This works out using shifts because bit and bit2 are known to
   // have only a single bit in them.
   wire [31:0] guess  = acc | bitm;
   wire [63:0] guess2 = acc2 + bit2 + ((acc << bitl) << 1);

   task clear;
      begin
	 acc = 0;
	 acc2 = 0;
	 bitl = 31;
      end
   endtask

   initial clear;

   always @(reset or posedge clk)
      if (reset)
       clear;
      else begin
	 if (guess2 <= x) begin
	    acc  <= guess;
	    acc2 <= guess2;
	 end
	 bitl <= bitl - 1;
      end

endmodule

module main;

   reg clk, reset;
   reg [63:0] value;
   wire [31:0] result;
   wire rdy;

   sqrt32 root(.clk(clk), .rdy(rdy), .reset(reset), .x(value), .y(result));

   always #5 clk = ~clk;

   always @(posedge rdy) begin
      $display("sqrt(%d) --> %d", value, result);
      $finish;
   end
initial begin
$dumpfile("sqrt64dump.vcd");
$dumpvars(0, main);
end


   initial begin
      clk = 0;
      reset = 1;
      $monitor($time,,"%m.acc = %b", root.acc);
      #100 value =64'd14446744073709551615;
      reset = 0;
   end
endmodule /* main */

project-287/sqrt64dump.vcd
$date
    Apr  7, 2015  13:22:45
$end
$version
    TOOL:	ncsim	14.10-p001
$end
$timescale
    1 ns
$end

$scope module main $end
$var reg       1 !    clk  $end
$var reg       1 "    reset  $end
$var reg      64 #    value [63:0] $end
$var wire     32 $    result [31:0] $end
$var wire      1 %    rdy  $end

$scope module root $end
$var wire      1 &    clk  $end
$var wire      1 %    rdy  $end
$var wire      1 '    reset  $end
$var wire     64 (    x [63:0] $end
$var reg      32 )    acc [31:0] $end
$var reg      64 *    acc2 [63:0] $end
$var reg       6 +    bitl [5:0] $end
$var wire     32 ,    bitm [31:0] $end
$var wire     64 -    bit2 [63:0] $end
$var wire     32 .    guess [31:0] $end
$var wire     64 /    guess2 [63:0] $end
$upscope $end

$upscope $end

$enddefinitions $end
$dumpvars
0!
1"
bx #
b0 $
0%
0&
1'
bx (
b0 )
b0 *
b11111 +
b10000000000000000000000000000000 ,
b100000000000000000000000000000000000000000000000000000000000000 -
b10000000000000000000000000000000 .
b100000000000000000000000000000000000000000000000000000000000000 /
$end
#5
1!
1&
#10
0!
0&
#15
1!
1&
#20
0!
0&
#25
1!
1&
#30
0!
0&
#35
1!
1&
#40
0!
0&
#45
1!
1&
#50
0!
0&
#55
1!
1&
#60
0!
0&
#65
1!
1&
#70
0!
0&
#75
1!
1&
#80
0!
0&
#85
1!
1&
#90
0!
0&
#95
1!
1&
#100
b1100100001111101001001010011000101100010011011111111111111111111 #
0"
0!
b1100100001111101001001010011000101100010011011111111111111111111 (
0&
0'
b10000000000000000000000000000000 )
b100000000000000000000000000000000000000000000000000000000000000 *
b11110 +
b1000000000000000000000000000000000000000000000000000000000000 -
b1000000000000000000000000000000 ,
b1100000000000000000000000000000000000000000000000000000000000000 /
b10000000000000000000000000000000 $
b11000000000000000000000000000000 .
b1001000000000000000000000000000000000000000000000000000000000000 /
#105
1!
1&
b11000000000000000000000000000000 )
b1001000000000000000000000000000000000000000000000000000000000000 *
b11101 +
b10000000000000000000000000000000000000000000000000000000000 -
b100000000000000000000000000000 ,
b1101000000000000000000000000000000000000000000000000000000000000 /
b11000000000000000000000000000000 $
b11100000000000000000000000000000 .
b1100010000000000000000000000000000000000000000000000000000000000 /
#110
0!
0&
#115
1!
1&
b11100000000000000000000000000000 )
b1100010000000000000000000000000000000000000000000000000000000000 *
b11100 +
b100000000000000000000000000000000000000000000000000000000 -
b10000000000000000000000000000 ,
b1110010000000000000000000000000000000000000000000000000000000000 /
b11100000000000000000000000000000 $
b11110000000000000000000000000000 .
b1110000100000000000000000000000000000000000000000000000000000000 /
#120
0!
0&
#125
1!
1&
b11011 +
b1101001100000000000000000000000000000000000000000000000000000000 /
b1000000000000000000000000000000000000000000000000000000 -
b1000000000000000000000000000 ,
b11101000000000000000000000000000 .
b1101001001000000000000000000000000000000000000000000000000000000 /
#130
0!
0&
#135
1!
1&
b11010 +
b1100101101000000000000000000000000000000000000000000000000000000 /
b10000000000000000000000000000000000000000000000000000 -
b100000000000000000000000000 ,
b11100100000000000000000000000000 .
b1100101100010000000000000000000000000000000000000000000000000000 /
#140
0!
0&
#145
1!
1&
b11001 +
b1100011110010000000000000000000000000000000000000000000000000000 /
b100000000000000000000000000000000000000000000000000 -
b10000000000000000000000000 ,
b11100010000000000000000000000000 .
b1100011110000100000000000000000000000000000000000000000000000000 /
#150
0!
0&
#155
1!
1&
b11100010000000000000000000000000 )
b1100011110000100000000000000000000000000000000000000000000000000 *
b11000 +
b1000000000000000000000000000000000000000000000000 -
b1000000000000000000000000 ,
b1100100101001100000000000000000000000000000000000000000000000000 /
b11100010000000000000000000000000 $
b11100011000000000000000000000000 .
b1100100101001001000000000000000000000000000000000000000000000000 /
#160
0!
0&
#165
1!
1&
b10111 +
b1100100001100111000000000000000000000000000000000000000000000000 /
b10000000000000000000000000000000000000000000000 -
b100000000000000000000000 ,
b11100010100000000000000000000000 .
b1100100001100110010000000000000000000000000000000000000000000000 /
#170
0!
0&
#175
1!
1&
b11100010100000000000000000000000 )
b1100100001100110010000000000000000000000000000000000000000000000 *
b10110 +
b100000000000000000000000000000000000000000000 -
b10000000000000000000000 ,
b1100100011010111110000000000000000000000000000000000000000000000 /
b11100010100000000000000000000000 $
b11100010110000000000000000000000 .
b1100100011010111100100000000000000000000000000000000000000000000 /
#180
0!
0&
#185
1!
1&
b10101 +
b1100100010011110111100000000000000000000000000000000000000000000 /
b1000000000000000000000000000000000000000000 -
b1000000000000000000000 ,
b11100010101000000000000000000000 .
b1100100010011110111001000000000000000000000000000000000000000000 /
#190
0!
0&
#195
1!
1&
b10100 +
b1100100010000010100101000000000000000000000000000000000000000000 /
b10000000000000000000000000000000000000000 -
b100000000000000000000 ,
b11100010100100000000000000000000 .
b1100100010000010100100010000000000000000000000000000000000000000 /
#200
0!
0&
#205
1!
1&
b10011 +
b1100100001110100011010010000000000000000000000000000000000000000 /
b100000000000000000000000000000000000000 -
b10000000000000000000 ,
b11100010100010000000000000000000 .
b1100100001110100011010000100000000000000000000000000000000000000 /
#210
0!
0&
#215
1!
1&
b11100010100010000000000000000000 )
b1100100001110100011010000100000000000000000000000000000000000000 *
b10010 +
b1000000000000000000000000000000000000 -
b1000000000000000000 ,
b1100100001111011011111001100000000000000000000000000000000000000 /
b11100010100010000000000000000000 $
b11100010100011000000000000000000 .
b1100100001111011011111001001000000000000000000000000000000000000 /
#220
0!
0&
#225
1!
1&
b11100010100011000000000000000000 )
b1100100001111011011111001001000000000000000000000000000000000000 *
b10001 +
b10000000000000000000000000000000000 -
b100000000000000000 ,
b1100100001111111000001101101000000000000000000000000000000000000 /
b11100010100011000000000000000000 $
b11100010100011100000000000000000 .
b1100100001111111000001101100010000000000000000000000000000000000 /
#230
0!
0&
#235
1!
1&
b10000 +
b1100100001111101010000011010110000000000000000000000000000000000 /
b100000000000000000000000000000000 -
b10000000000000000 ,
b11100010100011010000000000000000 .
b1100100001111101010000011010100100000000000000000000000000000000 /
#240
0!
0&
#245
1!
1&
b1111 +
b1100100001111100010111110001110100000000000000000000000000000000 /
b1000000000000000000000000000000 -
b1000000000000000 ,
b11100010100011001000000000000000 .
b1100100001111100010111110001110001000000000000000000000000000000 /
#250
0!
0&
#255
1!
1&
b11100010100011001000000000000000 )
b1100100001111100010111110001110001000000000000000000000000000000 *
b1110 +
b10000000000000000000000000000 -
b100000000000000 ,
b1100100001111100110100000110001011000000000000000000000000000000 /
b11100010100011001000000000000000 $
b11100010100011001100000000000000 .
b1100100001111100110100000110001010010000000000000000000000000000 /
#260
0!
0&
#265
1!
1&
b11100010100011001100000000000000 )
b1100100001111100110100000110001010010000000000000000000000000000 *
b1101 +
b100000000000000000000000000 -
b10000000000000 ,
b1100100001111101000010010000010111010000000000000000000000000000 /
b11100010100011001100000000000000 $
b11100010100011001110000000000000 .
b1100100001111101000010010000010111000100000000000000000000000000 /
#270
0!
0&
#275
1!
1&
b11100010100011001110000000000000 )
b1100100001111101000010010000010111000100000000000000000000000000 *
b1100 +
b1000000000000000000000000 -
b1000000000000 ,
b1100100001111101001001010101011101100100000000000000000000000000 /
b11100010100011001110000000000000 $
b11100010100011001111000000000000 .
b1100100001111101001001010101011101100001000000000000000000000000 /
#280
0!
0&
#285
1!
1&
b1011 +
b1100100001111101000101110010111010010011000000000000000000000000 /
b10000000000000000000000 -
b100000000000 ,
b11100010100011001110100000000000 .
b1100100001111101000101110010111010010010010000000000000000000000 /
#290
0!
0&
#295
1!
1&
b11100010100011001110100000000000 )
b1100100001111101000101110010111010010010010000000000000000000000 *
b1010 +
b100000000000000000000 -
b10000000000 ,
b1100100001111101000111100100001011111001110000000000000000000000 /
b11100010100011001110100000000000 $
b11100010100011001110110000000000 .
b1100100001111101000111100100001011111001100100000000000000000000 /
#300
0!
0&
#305
1!
1&
b11100010100011001110110000000000 )
b1100100001111101000111100100001011111001100100000000000000000000 *
b1001 +
b1000000000000000000 -
b1000000000 ,
b1100100001111101001000011100110100101101010100000000000000000000 /
b11100010100011001110110000000000 $
b11100010100011001110111000000000 .
b1100100001111101001000011100110100101101010001000000000000000000 /
#310
0!
0&
#315
1!
1&
b11100010100011001110111000000000 )
b1100100001111101001000011100110100101101010001000000000000000000 *
b1000 +
b10000000000000000 -
b100000000 ,
b1100100001111101001000111001001001000111001001000000000000000000 /
b11100010100011001110111000000000 $
b11100010100011001110111100000000 .
b1100100001111101001000111001001001000111001000010000000000000000 /
#320
0!
0&
#325
1!
1&
b11100010100011001110111100000000 )
b1100100001111101001000111001001001000111001000010000000000000000 *
b111 +
b100000000000000 -
b10000000 ,
b1100100001111101001001000111010011010100000100010000000000000000 /
b11100010100011001110111100000000 $
b11100010100011001110111110000000 .
b1100100001111101001001000111010011010100000100000100000000000000 /
#330
0!
0&
#335
1!
1&
b11100010100011001110111110000000 )
b1100100001111101001001000111010011010100000100000100000000000000 *
b110 +
b1000000000000 -
b1000000 ,
b1100100001111101001001001110011000011010100010000100000000000000 /
b11100010100011001110111110000000 $
b11100010100011001110111111000000 .
b1100100001111101001001001110011000011010100010000001000000000000 /
#340
0!
0&
#345
1!
1&
b11100010100011001110111111000000 )
b1100100001111101001001001110011000011010100010000001000000000000 *
b101 +
b10000000000 -
b100000 ,
b1100100001111101001001010001111010111101110001000001000000000000 /
b11100010100011001110111111000000 $
b11100010100011001110111111100000 .
b1100100001111101001001010001111010111101110001000000010000000000 /
#350
0!
0&
#355
1!
1&
b11100010100011001110111111100000 )
b1100100001111101001001010001111010111101110001000000010000000000 *
b100 +
b100000000 -
b10000 ,
b1100100001111101001001010011101100001111011000100000010000000000 /
b11100010100011001110111111100000 $
b11100010100011001110111111110000 .
b1100100001111101001001010011101100001111011000100000000100000000 /
#360
0!
0&
#365
1!
1&
b11 +
b1100100001111101001001010010110011100110100100110000001100000000 /
b1000000 -
b1000 ,
b11100010100011001110111111101000 .
b1100100001111101001001010010110011100110100100110000001001000000 /
#370
0!
0&
#375
1!
1&
b11100010100011001110111111101000 )
b1100100001111101001001010010110011100110100100110000001001000000 *
b10 +
b10000 -
b100 ,
b1100100001111101001001010011001111111010111110101000000111000000 /
b11100010100011001110111111101000 $
b11100010100011001110111111101100 .
b1100100001111101001001010011001111111010111110101000000110010000 /
#380
0!
0&
#385
1!
1&
b1 +
b1100100001111101001001010011000001110000110001101100000111110000 /
b100 -
b10 ,
b11100010100011001110111111101010 .
b1100100001111101001001010011000001110000110001101100000111100100 /
#390
0!
0&
#395
1!
1&
b11100010100011001110111111101010 )
b1100100001111101001001010011000001110000110001101100000111100100 *
b0 +
b1 -
b1 ,
b1100100001111101001001010011001000110101111000001010000110111100 /
b11100010100011001110111111101010 $
b11100010100011001110111111101011 .
b1100100001111101001001010011001000110101111000001010000110111001 /
#400
0!
0&
#405
1!
1&
b111111 +
b1100100001111101001001010011000001110000110001101100000111100101 /
b100000000000000000000000000000000000000000000000000000000000000 -
b0 ,
1%
